{"version": 0.6, "generator": "Overpass API 0.7.59 e21c39fe", "osm3s": {"timestamp_osm_base": "2023-01-30T21:06:39Z", "copyright": "The data included in this document is from www.openstreetmap.org. The data is made available under ODbL."}, "elements": [{"type": "node", "id": 4632328233, "lat": -23.4730835, "lon": -46.6843125}, {"type": "node", "id": 4632328234, "lat": -23.473519, "lon": -46.684114}, {"type": "node", "id": 4632328235, "lat": -23.4735067, "lon": -46.6840684}, {"type": "node", "id": 4632328236, "lat": -23.4735731, "lon": -46.6840362}, {"type": "node", "id": 4632328237, "lat": -23.4735337, "lon": -46.6838914}, {"type": "node", "id": 4632328238, "lat": -23.4735559, "lon": -46.6838833}, {"type": "node", "id": 4632328239, "lat": -23.4735362, "lon": -46.6838056}, {"type": "node", "id": 4632328240, "lat": -23.4734279, "lon": -46.6838109}, {"type": "node", "id": 4632328241, "lat": -23.4729777, "lon": -46.6840416}, {"type": "node", "id": 5370532522, "lat": -23.4732449, "lon": -46.6867056}, {"type": "node", "id": 5370532523, "lat": -23.4733245, "lon": -46.6866129}, {"type": "node", "id": 5370532524, "lat": -23.473436, "lon": -46.6867267}, {"type": "node", "id": 5370532525, "lat": -23.4733564, "lon": -46.6868194}, {"type": "node", "id": 5370548389, "lat": -23.4727173, "lon": -46.686828}, {"type": "node", "id": 5370548390, "lat": -23.4728286, "lon": -46.6869463}, {"type": "node", "id": 5370548391, "lat": -23.4729117, "lon": -46.6868534}, {"type": "node", "id": 5370548392, "lat": -23.4728005, "lon": -46.6867351}, {"type": "node", "id": 5370548393, "lat": -23.4730077, "lon": -46.6867692}, {"type": "node", "id": 5370548394, "lat": -23.4731062, "lon": -46.6866551}, {"type": "node", "id": 5370548395, "lat": -23.4731986, "lon": -46.68675}, {"type": "node", "id": 5370548396, "lat": -23.4731001, "lon": -46.6868641}, {"type": "node", "id": 5370548413, "lat": -23.472498, "lon": -46.6869065}, {"type": "node", "id": 5370548414, "lat": -23.4723904, "lon": -46.6867921}, {"type": "node", "id": 5370548415, "lat": -23.4724736, "lon": -46.686699}, {"type": "node", "id": 5370548416, "lat": -23.4725812, "lon": -46.6868134}, {"type": "node", "id": 5370549521, "lat": -23.4732624, "lon": -46.6865422}, {"type": "node", "id": 5370549522, "lat": -23.4731711, "lon": -46.6864473}, {"type": "node", "id": 5370549523, "lat": -23.4732728, "lon": -46.686331}, {"type": "node", "id": 5370549524, "lat": -23.4733641, "lon": -46.6864259}, {"type": "node", "id": 6380965252, "lat": -23.4721636, "lon": -46.6826801, "tags": {"addr:city": "S\u00e3o Paulo", "addr:housenumber": "430", "addr:postcode": "02864-030", "addr:street": "Rua Ipameri"}}, {"type": "node", "id": 6380965253, "lat": -23.4721445, "lon": -46.682744}, {"type": "node", "id": 6380965254, "lat": -23.4722012, "lon": -46.6825546}, {"type": "node", "id": 6380965255, "lat": -23.4720245, "lon": -46.6824799}, {"type": "node", "id": 6380965256, "lat": -23.472018, "lon": -46.6827104}, {"type": "node", "id": 6380965257, "lat": -23.472104, "lon": -46.6827781}, {"type": "node", "id": 6380965258, "lat": -23.4720574, "lon": -46.682749}, {"type": "node", "id": 6380965259, "lat": -23.4719799, "lon": -46.6826491}, {"type": "node", "id": 7252853560, "lat": -23.4728292, "lon": -46.6832023}, {"type": "node", "id": 7252853561, "lat": -23.4728601, "lon": -46.6830812}, {"type": "node", "id": 7252853562, "lat": -23.4726243, "lon": -46.6829864}, {"type": "node", "id": 7252853563, "lat": -23.4726003, "lon": -46.6830812}, {"type": "node", "id": 7252853564, "lat": -23.4726025, "lon": -46.6830937}, {"type": "node", "id": 7252853565, "lat": -23.472606, "lon": -46.6831049}, {"type": "node", "id": 7252853566, "lat": -23.4726107, "lon": -46.6830399, "tags": {"addr:city": "S\u00e3o Paulo", "addr:housenumber": "429", "addr:postcode": "02864-000", "addr:street": "Rua Lu\u00eds Jos\u00e9 Junqueira Freire"}}, {"type": "node", "id": 7252853567, "lat": -23.4727043, "lon": -46.6831478, "tags": {"addr:city": "S\u00e3o Paulo", "addr:housenumber": "2868", "addr:postcode": "02842-280", "addr:street": "Avenida Jo\u00e3o Paulo I"}}, {"type": "node", "id": 7252853576, "lat": -23.4721307, "lon": -46.6827556, "tags": {"addr:city": "S\u00e3o Paulo", "addr:housenumber": "432", "addr:postcode": "02864-030", "addr:street": "Rua Ipameri"}}, {"type": "node", "id": 7252853577, "lat": -23.472185, "lon": -46.6826088, "tags": {"addr:city": "S\u00e3o Paulo", "addr:housenumber": "426", "addr:postcode": "02864-030", "addr:street": "Rua Ipameri"}}, {"type": "node", "id": 7252853578, "lat": -23.4716272, "lon": -46.6839001}, {"type": "node", "id": 7252853579, "lat": -23.471508, "lon": -46.6837799}, {"type": "node", "id": 7252853580, "lat": -23.4716945, "lon": -46.68356}, {"type": "node", "id": 7252853581, "lat": -23.4718138, "lon": -46.6836803}, {"type": "node", "id": 7252853582, "lat": -23.4716757, "lon": -46.6835268}, {"type": "node", "id": 7252853583, "lat": -23.4719659, "lon": -46.6831926}, {"type": "node", "id": 7252853584, "lat": -23.472299, "lon": -46.6835364}, {"type": "node", "id": 7252878785, "lat": -23.4722396, "lon": -46.6836048}, {"type": "node", "id": 7252878786, "lat": -23.4719822, "lon": -46.683339}, {"type": "node", "id": 7252878787, "lat": -23.4718788, "lon": -46.6834581}, {"type": "node", "id": 7252878788, "lat": -23.4720651, "lon": -46.6836505}, {"type": "node", "id": 7252878789, "lat": -23.4719974, "lon": -46.6837284}, {"type": "node", "id": 7252878790, "lat": -23.4718194, "lon": -46.6835446}, {"type": "node", "id": 7252878791, "lat": -23.4717596, "lon": -46.6836135}, {"type": "node", "id": 7252878802, "lat": -23.4726474, "lon": -46.68393}, {"type": "node", "id": 7252878803, "lat": -23.4725752, "lon": -46.6837454}, {"type": "node", "id": 7252878804, "lat": -23.4729684, "lon": -46.6835625}, {"type": "node", "id": 7252878805, "lat": -23.4730406, "lon": -46.6837471}, {"type": "node", "id": 7252952586, "lat": -23.4728567, "lon": -46.6857919}, {"type": "node", "id": 7252952587, "lat": -23.4727654, "lon": -46.6856969}, {"type": "node", "id": 7252952588, "lat": -23.4728671, "lon": -46.6855806}, {"type": "node", "id": 7252952589, "lat": -23.4729584, "lon": -46.6856755}, {"type": "node", "id": 7252952590, "lat": -23.4726833, "lon": -46.6861915}, {"type": "node", "id": 7252952591, "lat": -23.472592, "lon": -46.6860965}, {"type": "node", "id": 7252952592, "lat": -23.4726937, "lon": -46.6859802}, {"type": "node", "id": 7252952593, "lat": -23.4727851, "lon": -46.6860751}, {"type": "node", "id": 7252952594, "lat": -23.4722719, "lon": -46.6859786}, {"type": "node", "id": 7252952595, "lat": -23.4721805, "lon": -46.6858837}, {"type": "node", "id": 7252952596, "lat": -23.4722674, "lon": -46.6857834}, {"type": "node", "id": 7252952597, "lat": -23.4723514, "lon": -46.6858568}, {"type": "node", "id": 7252952598, "lat": -23.4721152, "lon": -46.6854907}, {"type": "node", "id": 7252952599, "lat": -23.4720362, "lon": -46.6854092}, {"type": "node", "id": 7252952600, "lat": -23.4721379, "lon": -46.6852929}, {"type": "node", "id": 7252952601, "lat": -23.4722046, "lon": -46.6853797}, {"type": "node", "id": 7252952602, "lat": -23.4718804, "lon": -46.6861832}, {"type": "node", "id": 7252952603, "lat": -23.4717891, "lon": -46.6860883}, {"type": "node", "id": 7252952604, "lat": -23.4718908, "lon": -46.685972}, {"type": "node", "id": 7252952605, "lat": -23.4719821, "lon": -46.6860669}, {"type": "node", "id": 7252952606, "lat": -23.4720467, "lon": -46.6866292}, {"type": "node", "id": 7252952607, "lat": -23.4719554, "lon": -46.6865343}, {"type": "node", "id": 7252952608, "lat": -23.4720571, "lon": -46.686418}, {"type": "node", "id": 7252952609, "lat": -23.4721484, "lon": -46.6865129}, {"type": "node", "id": 7252952610, "lat": -23.471691, "lon": -46.6869043}, {"type": "node", "id": 7252952611, "lat": -23.4715997, "lon": -46.6868094}, {"type": "node", "id": 7252952612, "lat": -23.4717014, "lon": -46.686693}, {"type": "node", "id": 7252952613, "lat": -23.4717927, "lon": -46.6867879}, {"type": "node", "id": 7252952614, "lat": -23.4713997, "lon": -46.6869046}, {"type": "node", "id": 7252952615, "lat": -23.4713083, "lon": -46.6868097}, {"type": "node", "id": 7252952616, "lat": -23.47141, "lon": -46.6866934}, {"type": "node", "id": 7252952617, "lat": -23.4715014, "lon": -46.6867883}, {"type": "node", "id": 7252952642, "lat": -23.4719751, "lon": -46.686948}, {"type": "node", "id": 7252952643, "lat": -23.471864, "lon": -46.6868292}, {"type": "node", "id": 7252952644, "lat": -23.4719523, "lon": -46.6867498}, {"type": "node", "id": 7252952645, "lat": -23.4720486, "lon": -46.6868579}, {"type": "node", "id": 7252952646, "lat": -23.471807, "lon": -46.6866254}, {"type": "node", "id": 7252952647, "lat": -23.471696, "lon": -46.6865066}, {"type": "node", "id": 7252952648, "lat": -23.4717842, "lon": -46.6864085}, {"type": "node", "id": 7252952649, "lat": -23.4718953, "lon": -46.6865274}, {"type": "node", "id": 7252952650, "lat": -23.4721777, "lon": -46.6862621}, {"type": "node", "id": 7252952651, "lat": -23.4720864, "lon": -46.6861648}, {"type": "node", "id": 7252952652, "lat": -23.4721746, "lon": -46.6860667}, {"type": "node", "id": 7252952653, "lat": -23.4722586, "lon": -46.686164}, {"type": "node", "id": 7252952654, "lat": -23.4719858, "lon": -46.6858431}, {"type": "node", "id": 7252952655, "lat": -23.4718796, "lon": -46.6857646}, {"type": "node", "id": 7252952656, "lat": -23.4719433, "lon": -46.6856933}, {"type": "node", "id": 7252952657, "lat": -23.4720298, "lon": -46.6857881}, {"type": "node", "id": 7252952658, "lat": -23.4725938, "lon": -46.6858602}, {"type": "node", "id": 7252952659, "lat": -23.4724925, "lon": -46.6857628}, {"type": "node", "id": 7252952660, "lat": -23.4725636, "lon": -46.6856835}, {"type": "node", "id": 7252952661, "lat": -23.4726575, "lon": -46.6857836}, {"type": "node", "id": 7252952662, "lat": -23.4724699, "lon": -46.6855565}, {"type": "node", "id": 7252952663, "lat": -23.4723661, "lon": -46.6854457}, {"type": "node", "id": 7252952664, "lat": -23.4724298, "lon": -46.6853691}, {"type": "node", "id": 7252952665, "lat": -23.4725459, "lon": -46.6854638}, {"type": "node", "id": 7252952666, "lat": -23.4729737, "lon": -46.6861094}, {"type": "node", "id": 7252952667, "lat": -23.4728626, "lon": -46.6859905}, {"type": "node", "id": 7252952668, "lat": -23.4729509, "lon": -46.6858924}, {"type": "node", "id": 7252952669, "lat": -23.473062, "lon": -46.6860113}, {"type": "node", "id": 7252989523, "lat": -23.4726598, "lon": -46.684359}, {"type": "node", "id": 7252989524, "lat": -23.4726051, "lon": -46.6842197}, {"type": "node", "id": 7252989525, "lat": -23.4728201, "lon": -46.6841192}, {"type": "node", "id": 7252989526, "lat": -23.4728749, "lon": -46.6842584}, {"type": "way", "id": 468762630, "nodes": [4632328233, 4632328234, 4632328235, 4632328236, 4632328237, 4632328238, 4632328239, 4632328240, 4632328241, 4632328233], "tags": {"addr:city": "S\u00e3o Paulo", "addr:housenumber": "2", "addr:street": "Rua Rui de Morais Apocalipse", "addr:suburb": "Vila Penteado", "alt_name": "Redel Hora Certa", "amenity": "clinic", "building": "yes", "healthcare": "clinic", "name": "UBS Maria Cec\u00edlia Ferreira Donnangelo"}}, {"type": "way", "id": 556783150, "nodes": [5370532522, 5370532523, 5370532524, 5370532525, 5370532522], "tags": {"building": "residential", "height": "48"}}, {"type": "way", "id": 556784018, "nodes": [5370548389, 5370548390, 5370548391, 5370548392, 5370548389], "tags": {"building": "yes", "height": "48"}}, {"type": "way", "id": 556784019, "nodes": [5370548393, 5370548394, 5370548395, 5370548396, 5370548393], "tags": {"building": "residential", "height": "48"}}, {"type": "way", "id": 556784024, "nodes": [5370548413, 5370548414, 5370548415, 5370548416, 5370548413], "tags": {"building": "residential", "height": "48"}}, {"type": "way", "id": 556784026, "nodes": [5370549521, 5370549522, 5370549523, 5370549524, 5370549521], "tags": {"building": "residential", "height": "48"}}, {"type": "way", "id": 681390032, "nodes": [6380965253, 6380965252, 7252853577, 6380965254, 6380965255, 6380965259, 6380965256, 6380965258, 6380965257, 7252853576, 6380965253], "tags": {"addr:city": "S\u00e3o Paulo", "addr:housenumber": "432", "addr:postcode": "02864-030", "addr:street": "Rua Ipameri", "building": "yes", "name": "Alves P\u00e3es e Do\u00e7es", "shop": "bakery"}}, {"type": "way", "id": 777280826, "nodes": [7252853560, 7252853561, 7252853562, 7252853566, 7252853563, 7252853564, 7252853565, 7252853567, 7252853560], "tags": {"addr:city": "S\u00e3o Paulo", "addr:housenumber": "2868", "addr:postcode": "02842-280", "addr:street": "Avenida Jo\u00e3o Paulo I", "building": "yes", "height": "8", "name": "Rei do \u00d3leo", "payment:cash": "yes", "payment:credit_cards": "yes", "payment:debit_cards": "yes", "phone": "+55 11 3851-6460", "service:vehicle:oil_change": "yes", "shop": "car_repair"}}, {"type": "way", "id": 777280830, "nodes": [7252853578, 7252853579, 7252853580, 7252853581, 7252853578], "tags": {"building": "yes", "height": "9"}}, {"type": "way", "id": 777280831, "nodes": [7252853582, 7252853583, 7252853584, 7252878785, 7252878786, 7252878787, 7252878788, 7252878789, 7252878790, 7252878791, 7252853582], "tags": {"addr:city": "S\u00e3o Paulo", "addr:housenumber": "49", "addr:postcode": "02867-000", "addr:street": "Rua Caiap\u00e9", "alt_name": "E.E Chiquinha Rodrigues", "amenity": "school", "building": "yes", "height": "10", "name": "Escola Estadual Chiquinha Rodrigues"}}, {"type": "way", "id": 777280833, "nodes": [7252878802, 7252878803, 7252878804, 7252878805, 7252878802], "tags": {"addr:city": "S\u00e3o Paulo", "addr:housenumber": "469", "addr:postcode": "02842-280", "addr:street": "Rua Lu\u00eds Jos\u00e9 Junqueira Freire", "building": "yes", "height": "10", "name": "Sacol\u00e3o Freguesia do \u00d3", "operator": "PMSP", "shop": "greengrocer"}}, {"type": "way", "id": 777288669, "nodes": [7252952586, 7252952587, 7252952588, 7252952589, 7252952586], "tags": {"building": "residential", "height": "48"}}, {"type": "way", "id": 777288670, "nodes": [7252952590, 7252952591, 7252952592, 7252952593, 7252952590], "tags": {"building": "residential", "height": "48"}}, {"type": "way", "id": 777288671, "nodes": [7252952594, 7252952595, 7252952596, 7252952597, 7252952594], "tags": {"building": "residential", "height": "48"}}, {"type": "way", "id": 777288672, "nodes": [7252952598, 7252952599, 7252952600, 7252952601, 7252952598], "tags": {"building": "residential", "height": "48"}}, {"type": "way", "id": 777288673, "nodes": [7252952602, 7252952603, 7252952604, 7252952605, 7252952602], "tags": {"building": "residential", "height": "48"}}, {"type": "way", "id": 777288674, "nodes": [7252952606, 7252952607, 7252952608, 7252952609, 7252952606], "tags": {"building": "residential", "height": "48"}}, {"type": "way", "id": 777288675, "nodes": [7252952610, 7252952611, 7252952612, 7252952613, 7252952610], "tags": {"building": "residential", "height": "48"}}, {"type": "way", "id": 777288676, "nodes": [7252952614, 7252952615, 7252952616, 7252952617, 7252952614], "tags": {"building": "yes", "height": "48"}}, {"type": "way", "id": 777288683, "nodes": [7252952642, 7252952643, 7252952644, 7252952645, 7252952642], "tags": {"building": "residential", "height": "48"}}, {"type": "way", "id": 777288684, "nodes": [7252952646, 7252952647, 7252952648, 7252952649, 7252952646], "tags": {"building": "residential", "height": "48"}}, {"type": "way", "id": 777288685, "nodes": [7252952650, 7252952651, 7252952652, 7252952653, 7252952650], "tags": {"building": "residential", "height": "48"}}, {"type": "way", "id": 777288686, "nodes": [7252952654, 7252952655, 7252952656, 7252952657, 7252952654], "tags": {"building": "residential", "height": "48"}}, {"type": "way", "id": 777288687, "nodes": [7252952658, 7252952659, 7252952660, 7252952661, 7252952658], "tags": {"building": "residential", "height": "48"}}, {"type": "way", "id": 777288688, "nodes": [7252952662, 7252952663, 7252952664, 7252952665, 7252952662], "tags": {"building": "residential", "height": "48"}}, {"type": "way", "id": 777288689, "nodes": [7252952666, 7252952667, 7252952668, 7252952669, 7252952666], "tags": {"building": "residential", "height": "48"}}, {"type": "way", "id": 777295887, "nodes": [7252989523, 7252989524, 7252989525, 7252989526, 7252989523], "tags": {"addr:city": "S\u00e3o Paulo", "addr:housenumber": "571", "addr:postcode": "02842-280", "addr:street": "Rua Lu\u00eds Jos\u00e9 Junqueira Freire", "amenity": "childcare", "building": "yes", "height": "8", "name": "C.E.I Vila Penteado"}}]}